CHANGELOG
COPYING
INSTALL
MANIFEST.in
README.rst
setup.cfg
setup.py
should_dingus.py
tests.py
should_dingus.egg-info/PKG-INFO
should_dingus.egg-info/SOURCES.txt
should_dingus.egg-info/dependency_links.txt
should_dingus.egg-info/requires.txt
should_dingus.egg-info/top_level.txt