Metadata-Version: 1.0
Name: should-dingus
Version: 0.3
Summary: Dingus call matcher for should-dsl
Home-page: https://github.com/CharString/should-dingus
Author: Chris Wesseling
Author-email: chris.wesseling@cwi.nl
License: BSD
Keywords: dingus should dsl testing test mocking mock double stub fake record assert bdd python expectation
Platform: UNKNOWN
Classifier: Development Status :: 4 - Beta
Classifier: Intended Audience :: Developers
Classifier: License :: OSI Approved :: BSD License
Classifier: Operating System :: OS Independent
Classifier: Programming Language :: Python
Classifier: Topic :: Software Development :: Testing
